README.md
setup.py
route_logger_fastapi_middleware.egg-info/PKG-INFO
route_logger_fastapi_middleware.egg-info/SOURCES.txt
route_logger_fastapi_middleware.egg-info/dependency_links.txt
route_logger_fastapi_middleware.egg-info/requires.txt
route_logger_fastapi_middleware.egg-info/top_level.txt
route_logger_middleware/__init__.py
route_logger_middleware/backends/__init__.py
route_logger_middleware/backends/kafka_backend.py
route_logger_middleware/backends/mqtt_backend.py
route_logger_middleware/backends/print_logger_backend.py
route_logger_middleware/backends/rabbit_mq_backend.py
route_logger_middleware/backends/redis_backend.py