Metadata-Version: 2.1
Name: route-logger-fastapi-middleware
Version: 0.0.1
Summary: A middleware to log all requests in FastAPI
Home-page: https://github.com/iudeen/fastapi-route-logger
Author: irfanuddin
Author-email: irfanudeen08@gmail.com
License: MIT
Platform: UNKNOWN
Provides-Extra: kafka
Provides-Extra: mqtt
Provides-Extra: redis
